{
  "generated_at": "2026-05-12T17:39:25.451744+00:00",
  "articles": [
    {
      "id": "e0f736379155",
      "title": "Brazil Meat Left Out of Europe Suppliers List in Risk to Trade",
      "source": "Bloomberg Markets",
      "url": "https://www.bloomberg.com/news/articles/2026-05-12/brazil-meat-left-out-of-europe-suppliers-list-in-risk-to-trade",
      "published_at": "2026-05-12T17:28:52+00:00",
      "category": "other",
      "sentiment": "neutral",
      "signal": "watch",
      "summary": "Brazil is absent from a list of countries authorized to supply animal products to the European Union, presenting a trade risk to the world’s largest beef exporter.",
      "tags": []
    },
    {
      "id": "a5ba96d792a6",
      "title": "AI Boom Shows Top US Grid ‘Too Big to Function,’ Regulator Says",
      "source": "Bloomberg Markets",
      "url": "https://www.bloomberg.com/news/articles/2026-05-12/biggest-us-grid-may-be-too-large-to-function-regulator-says",
      "published_at": "2026-05-12T15:45:27+00:00",
      "category": "other",
      "sentiment": "neutral",
      "signal": "watch",
      "summary": "The chairman of the top US energy regulator has put America’s biggest power grid on notice, warning that its operator may be too big to function adequately amid the AI data center boom.",
      "tags": []
    },
    {
      "id": "c8f99eb5fe5f",
      "title": "Boeing Bets Comeback on Trump, China and an Elusive New Plane",
      "source": "Bloomberg Markets",
      "url": "https://www.bloomberg.com/news/videos/2026-05-12/boeing-bets-comeback-on-trump-china-elusive-new-plane-video",
      "published_at": "2026-05-12T17:27:24+00:00",
      "category": "other",
      "sentiment": "neutral",
      "signal": "watch",
      "summary": "When Richard Nixon landed in Beijing in 1972 to end a quarter-century of Chinese diplomatic and economic isolation, his hosts were so enthralled with the US president’s airliner that within months the",
      "tags": []
    },
    {
      "id": "18a8abaa2fd2",
      "title": "New Jersey ICE Warehouse Paused as US to Weigh Green Impact",
      "source": "Bloomberg Markets",
      "url": "https://www.bloomberg.com/news/articles/2026-05-12/new-jersey-ice-detention-project-paused-as-us-to-conduct-review",
      "published_at": "2026-05-12T16:48:23+00:00",
      "category": "other",
      "sentiment": "neutral",
      "signal": "watch",
      "summary": "The federal government agreed to review the environmental impact of a proposed immigrant detention facility in New Jersey and temporarily pause a lawsuit seeking to block the conversion of an industri",
      "tags": []
    },
    {
      "id": "91c5acdc2e7c",
      "title": "Copper Rallies Above $14,000 a Ton, Nearing Fresh All-Time High",
      "source": "Bloomberg Markets",
      "url": "https://www.bloomberg.com/news/articles/2026-05-12/copper-rallies-above-14-000-a-ton-nearing-fresh-all-time-high",
      "published_at": "2026-05-12T14:11:31+00:00",
      "category": "other",
      "sentiment": "neutral",
      "signal": "watch",
      "summary": "Copper jumped above $14,000 a ton, closing in on a record high as a rebound in Chinese demand and mounting supply risks outweigh concerns about the Iran war’s impact on global growth.",
      "tags": []
    },
    {
      "id": "854ad0a5ee79",
      "title": "Dimon Says JPMorgan Would Scrap UK HQ Over Higher Bank Taxes",
      "source": "Bloomberg Markets",
      "url": "https://www.bloomberg.com/news/articles/2026-05-12/dimon-says-jpmorgan-would-scrap-new-uk-hq-over-higher-bank-taxes",
      "published_at": "2026-05-12T15:09:09+00:00",
      "category": "other",
      "sentiment": "neutral",
      "signal": "watch",
      "summary": "Jamie Dimon warned the UK that any move to hike taxes on banks in the event Keir Starmer is replaced as the UK’s prime minster would see JPMorgan Chase &amp; Co. scrap plans to invest billions in a ne",
      "tags": []
    },
    {
      "id": "09c8a0d6b5ea",
      "title": "Chip Stocks Sink as Inflation Woes Boost US Yields: Markets Wrap",
      "source": "Bloomberg Markets",
      "url": "https://www.bloomberg.com/news/articles/2026-05-11/asia-stocks-to-gain-oil-rises-on-us-iran-deadlock-markets-wrap",
      "published_at": "2026-05-11T22:04:02+00:00",
      "category": "other",
      "sentiment": "neutral",
      "signal": "watch",
      "summary": "A selloff in high-flying chipmakers drove stocks lower, with the market also falling alongside bonds after inflation data showed the impacts of energy disruptions stemming from the war in Iran.",
      "tags": []
    },
    {
      "id": "76248556e937",
      "title": "Russia Sees 2026 Oil Output Flat as Kyiv Steps Up Drone Strikes",
      "source": "Bloomberg Markets",
      "url": "https://www.bloomberg.com/news/articles/2026-05-12/russia-sees-2026-oil-output-flat-as-kyiv-steps-up-drone-strikes",
      "published_at": "2026-05-12T17:00:31+00:00",
      "category": "other",
      "sentiment": "neutral",
      "signal": "watch",
      "summary": "Russia expects its oil production to remain flat in 2026 and grow modestly in the coming two years as its energy infrastructure comes under intense drone attacks from Ukraine.",
      "tags": []
    },
    {
      "id": "4685a035314b",
      "title": "Emerging-Market Currencies, Stocks Fall as Iran Truce Hopes Dim",
      "source": "Bloomberg Markets",
      "url": "https://www.bloomberg.com/news/articles/2026-05-12/emerging-market-currencies-stocks-fall-as-iran-peace-hopes-dim",
      "published_at": "2026-05-12T09:44:52+00:00",
      "category": "other",
      "sentiment": "neutral",
      "signal": "watch",
      "summary": "Emerging-market currencies and stocks dropped Tuesday on concern the ceasefire between the US and Iran is on the brink of collapse, while a slump in South Korean shares also weighed on sentiment.",
      "tags": []
    },
    {
      "id": "ed98a8ac7c58",
      "title": "An 82% Earnings Drop at US LBM Shows Pain in Building Materials",
      "source": "Bloomberg Markets",
      "url": "https://www.bloomberg.com/news/articles/2026-05-12/an-82-earnings-drop-at-us-lbm-shows-pain-in-building-materials",
      "published_at": "2026-05-12T16:56:30+00:00",
      "category": "other",
      "sentiment": "neutral",
      "signal": "watch",
      "summary": "Building materials and products distributor US LBM Holdings reported sharply weaker first-quarter earnings as operating expenses ramped up and demand continued to soften in one of the starkest example",
      "tags": []
    },
    {
      "id": "8a4beb3b0ec1",
      "title": "US inflation jumps to 3.8% as Trump’s Iran war sends petrol prices soaring",
      "source": "International homepage",
      "url": "https://www.ft.com/content/ce609605-8f82-42d7-8364-5ca5fbfb02cb",
      "published_at": "2026-05-12T15:49:16+00:00",
      "category": "other",
      "sentiment": "neutral",
      "signal": "watch",
      "summary": "April figure marks highest level in three years as effects of conflict reverberate through world’s biggest economy",
      "tags": []
    },
    {
      "id": "da6721210649",
      "title": "Kevin Warsh to face resurgent inflation and an impatient Trump as Fed chair",
      "source": "International homepage",
      "url": "https://www.ft.com/content/af3bc83f-8a3c-4280-aa80-9d16bbd0cb6d",
      "published_at": "2026-05-12T04:00:18+00:00",
      "category": "other",
      "sentiment": "neutral",
      "signal": "watch",
      "summary": "US Senate widely expected to confirm the 56-year-old financier to replace Jay Powell this week",
      "tags": []
    },
    {
      "id": "bd0f1e79b48a",
      "title": "Don’t mess with central bank independence",
      "source": "International homepage",
      "url": "https://www.ft.com/content/46d8fac2-a90d-45d8-9a64-bc2483cf5963",
      "published_at": "2026-05-12T11:30:10+00:00",
      "category": "other",
      "sentiment": "neutral",
      "signal": "watch",
      "summary": "A wave of new research suggests Donald Trump is taking significant risks with his assaults on the US Federal Reserve",
      "tags": []
    },
    {
      "id": "753935215121",
      "title": "Trump loses his trade superpower",
      "source": "International homepage",
      "url": "https://www.ft.com/content/66a5c6c7-1b2b-47cc-9e07-77a87625fdfa",
      "published_at": "2026-05-12T04:00:09+00:00",
      "category": "other",
      "sentiment": "neutral",
      "signal": "watch",
      "summary": "‘Tariff man’ wants to recover from a wounding Supreme Court ruling. But Congress is restive and voters are unhappy",
      "tags": []
    },
    {
      "id": "42379d1634e0",
      "title": "Why Americans dread AI",
      "source": "International homepage",
      "url": "https://www.ft.com/content/637f5664-44eb-4527-8369-9eec320cfdf0",
      "published_at": "2026-05-12T11:04:25+00:00",
      "category": "other",
      "sentiment": "neutral",
      "signal": "watch",
      "summary": "Silicon Valley encourages the view that the technology is unstoppable — and Trump seems to agree",
      "tags": []
    },
    {
      "id": "65761c729af9",
      "title": "We are living in the age of asymmetry",
      "source": "International homepage",
      "url": "https://www.ft.com/content/5fefc72b-aded-46d6-b509-1904204ca8b0",
      "published_at": "2026-05-12T04:00:18+00:00",
      "category": "other",
      "sentiment": "neutral",
      "signal": "watch",
      "summary": "Power flows less from size or wealth than from the ability to convert imbalance into leverage",
      "tags": []
    },
    {
      "id": "53b8cbd15b5f",
      "title": "Four ministers resign as Starmer vows to fight on",
      "source": "International homepage",
      "url": "https://www.ft.com/content/c2455a7b-8cb5-42f9-9515-6ae664341e26",
      "published_at": "2026-05-12T15:41:59+00:00",
      "category": "other",
      "sentiment": "neutral",
      "signal": "watch",
      "summary": "PM challenges rivals to launch formal leadership contest",
      "tags": []
    },
    {
      "id": "6441506c7988",
      "title": "UK borrowing costs surge as Starmer leadership crisis rattles bond markets",
      "source": "International homepage",
      "url": "https://www.ft.com/content/4bd1dadd-3a1c-4adf-b255-0b03f7e8c36d",
      "published_at": "2026-05-12T16:30:25+00:00",
      "category": "other",
      "sentiment": "neutral",
      "signal": "watch",
      "summary": "Thirty-year gilt yield at highest this century as cabinet ministers pressure PM to consider his position",
      "tags": []
    },
    {
      "id": "1e9b89f43f07",
      "title": "Group linked to Trump sons asks US for extra $400mn for tungsten mine",
      "source": "International homepage",
      "url": "https://www.ft.com/content/80b47fe6-f752-4f5e-9507-fe0d14934e72",
      "published_at": "2026-05-12T16:25:36+00:00",
      "category": "other",
      "sentiment": "neutral",
      "signal": "watch",
      "summary": "Cove Kaz Capital has already secured up to $1.6bn in government support for project in Kazakhstan",
      "tags": []
    },
    {
      "id": "71c5286dffb6",
      "title": "Blue Owl retail fundraising evaporates amid private credit concerns",
      "source": "International homepage",
      "url": "https://www.ft.com/content/d04547c7-6315-4998-928d-2708670f4e01",
      "published_at": "2026-05-12T17:20:21+00:00",
      "category": "other",
      "sentiment": "neutral",
      "signal": "watch",
      "summary": "Fund it operates took in fraction of capital from year-ago level as worries mount over potential surge in loan defaults",
      "tags": []
    },
    {
      "id": "78f7a83e386d",
      "title": "Here’s what happened in crypto today",
      "source": "Cointelegraph.com News",
      "url": "https://cointelegraph.com/news/what-happened-in-crypto-today?utm_source=rss_feed&utm_medium=rss&utm_campaign=rss_partner_inbound",
      "published_at": "2026-05-12T14:37:33+00:00",
      "category": "other",
      "sentiment": "neutral",
      "signal": "watch",
      "summary": "<p style=\"float: right; margin: 0 0 10px 15px; width: 240px;\"><img alt=\"Here’s what happened in crypto today\" class=\"type:primaryImage\" src=\"https://images.cointelegraph.com/images/528_aHR0cHM6Ly9zMy1",
      "tags": []
    },
    {
      "id": "96a87a49d693",
      "title": "Bitcoin digests highest US CPI since 2023 as Fed rate hike woes return",
      "source": "Cointelegraph.com News",
      "url": "https://cointelegraph.com/markets/bitcoin-digests-highest-us-cpi-print-since-2023-fed-rate-hike-nerves-return?utm_source=rss_feed&utm_medium=rss&utm_campaign=rss_partner_inbound",
      "published_at": "2026-05-12T14:33:51+00:00",
      "category": "other",
      "sentiment": "neutral",
      "signal": "watch",
      "summary": "<p style=\"float: right; margin: 0 0 10px 15px; width: 240px;\"><img alt=\"Bitcoin digests highest US CPI since 2023 as Fed rate hike woes return\" class=\"type:primaryImage\" src=\"https://images.cointelegr",
      "tags": []
    },
    {
      "id": "6a4d29355af6",
      "title": "LMAX Group launches digital asset collateral solution for institutions",
      "source": "Cointelegraph.com News",
      "url": "https://cointelegraph.com/news/lmax-group-launches-digital-asset-collateral-solution-institutions?utm_source=rss_feed&utm_medium=rss&utm_campaign=rss_partner_inbound",
      "published_at": "2026-05-12T14:15:17+00:00",
      "category": "other",
      "sentiment": "neutral",
      "signal": "watch",
      "summary": "<p style=\"float: right; margin: 0 0 10px 15px; width: 240px;\"><img alt=\"LMAX Group launches digital asset collateral solution for institutions\" class=\"type:primaryImage\" src=\"https://images.cointelegr",
      "tags": []
    },
    {
      "id": "00de2855a9a5",
      "title": "Exodus sells over 1,000 Bitcoin as Q1 loss widens to $32M",
      "source": "Cointelegraph.com News",
      "url": "https://cointelegraph.com/news/exodus-posts-32m-loss-in-q1-sells-63-of-its-bitcoin-holdings-to-fund-acquisitions?utm_source=rss_feed&utm_medium=rss&utm_campaign=rss_partner_inbound",
      "published_at": "2026-05-12T14:05:01+00:00",
      "category": "other",
      "sentiment": "neutral",
      "signal": "watch",
      "summary": "<p style=\"float: right; margin: 0 0 10px 15px; width: 240px;\"><img alt=\"Exodus sells over 1,000 Bitcoin as Q1 loss widens to $32M\" class=\"type:primaryImage\" src=\"https://images.cointelegraph.com/image",
      "tags": []
    },
    {
      "id": "7737d4373673",
      "title": "FalconX expands tokenized credit facility to Monad network in lending push",
      "source": "Cointelegraph.com News",
      "url": "https://cointelegraph.com/news/falconx-expands-tokenized-credit-facility-to-monad-network?utm_source=rss_feed&utm_medium=rss&utm_campaign=rss_partner_inbound",
      "published_at": "2026-05-12T14:00:00+00:00",
      "category": "other",
      "sentiment": "neutral",
      "signal": "watch",
      "summary": "<p style=\"float: right; margin: 0 0 10px 15px; width: 240px;\"><img alt=\"FalconX expands tokenized credit facility to Monad network in lending push\" class=\"type:primaryImage\" src=\"https://images.cointe",
      "tags": []
    },
    {
      "id": "b836da556fa3",
      "title": "North Korea ‘industrialized’ crypto theft, laundered billions: CertiK",
      "source": "Cointelegraph.com News",
      "url": "https://cointelegraph.com/news/north-korea-industrialized-crypto-theft-laundered-billions-report-finds?utm_source=rss_feed&utm_medium=rss&utm_campaign=rss_partner_inbound",
      "published_at": "2026-05-12T14:00:00+00:00",
      "category": "other",
      "sentiment": "neutral",
      "signal": "watch",
      "summary": "<p style=\"float: right; margin: 0 0 10px 15px; width: 240px;\"><img alt=\"North Korea ‘industrialized’ crypto theft, laundered billions: CertiK\" class=\"type:primaryImage\" src=\"https://images.cointelegra",
      "tags": []
    },
    {
      "id": "c42064241b8a",
      "title": "Bitcoin whale 'still short' BTC despite facing $13M in losses",
      "source": "Cointelegraph.com News",
      "url": "https://cointelegraph.com/markets/bitcoin-bear-down-13m-btc-short-analysts-predict-new-bull-market?utm_source=rss_feed&utm_medium=rss&utm_campaign=rss_partner_inbound",
      "published_at": "2026-05-12T13:56:05+00:00",
      "category": "other",
      "sentiment": "neutral",
      "signal": "watch",
      "summary": "<p style=\"float: right; margin: 0 0 10px 15px; width: 240px;\"><img alt=\"Bitcoin whale 'still short' BTC despite facing $13M in losses\" class=\"type:primaryImage\" src=\"https://images.cointelegraph.com/i",
      "tags": []
    },
    {
      "id": "a323523cf053",
      "title": "Bitcoin may avoid historic bear market losses as ETF flows grow, says analyst",
      "source": "Cointelegraph.com News",
      "url": "https://cointelegraph.com/markets/bitcoin-may-avoid-historic-bear-market-losses-etf-flows-grow-says-analyst?utm_source=rss_feed&utm_medium=rss&utm_campaign=rss_partner_inbound",
      "published_at": "2026-05-12T13:49:44+00:00",
      "category": "other",
      "sentiment": "neutral",
      "signal": "watch",
      "summary": "<p style=\"float: right; margin: 0 0 10px 15px; width: 240px;\"><img alt=\"Bitcoin may avoid historic bear market losses as ETF flows grow, says analyst\" class=\"type:primaryImage\" src=\"https://images.coi",
      "tags": []
    },
    {
      "id": "6165ac6abed8",
      "title": "Roaring Kitty-linked RKC memecoin crashes as developer cashes out $729K",
      "source": "Cointelegraph.com News",
      "url": "https://cointelegraph.com/news/memecoin-dev-cashes-out-729k-gamestop-orchestrators-x-post?utm_source=rss_feed&utm_medium=rss&utm_campaign=rss_partner_inbound",
      "published_at": "2026-05-12T13:44:12+00:00",
      "category": "other",
      "sentiment": "neutral",
      "signal": "watch",
      "summary": "<p style=\"float: right; margin: 0 0 10px 15px; width: 240px;\"><img alt=\"Roaring Kitty-linked RKC memecoin crashes as developer cashes out $729K\" class=\"type:primaryImage\" src=\"https://images.cointeleg",
      "tags": []
    },
    {
      "id": "9a9606f73617",
      "title": "Four signs that Bitcoin has recovered to ‘full’ bullish momentum",
      "source": "Cointelegraph.com News",
      "url": "https://cointelegraph.com/markets/four-signs-bitcoin-recovered-full-bullish-momentum?utm_source=rss_feed&utm_medium=rss&utm_campaign=rss_partner_inbound",
      "published_at": "2026-05-12T13:32:06+00:00",
      "category": "other",
      "sentiment": "neutral",
      "signal": "watch",
      "summary": "<p style=\"float: right; margin: 0 0 10px 15px; width: 240px;\"><img alt=\"Four signs that Bitcoin has recovered to ‘full’ bullish momentum\" class=\"type:primaryImage\" src=\"https://images.cointelegraph.co",
      "tags": []
    },
    {
      "id": "8a9e231d3f4f",
      "title": "The Ethereum Foundation unveils new 'Clear Signing' standard to stop users from approving malicious crypto transactions",
      "source": "CoinDesk: Bitcoin, Ethereum, Crypto News and Price Data",
      "url": "https://www.coindesk.com/tech/2026/05/12/the-ethereum-foundation-unveils-new-clear-signing-standard-to-stop-users-from-approving-malicious-crypto-transactions",
      "published_at": "2026-05-12T17:31:53+00:00",
      "category": "other",
      "sentiment": "neutral",
      "signal": "watch",
      "summary": "The Ethereum Foundation unveils new 'Clear Signing' standard to stop users from approving malicious crypto transactions",
      "tags": []
    },
    {
      "id": "a86462fe989f",
      "title": "Senate confirms Kevin Warsh to Fed board ahead of expected Chair vote",
      "source": "CoinDesk: Bitcoin, Ethereum, Crypto News and Price Data",
      "url": "https://www.coindesk.com/policy/2026/05/12/senate-confirms-kevin-warsh-to-fed-board-ahead-of-expected-chair-vote",
      "published_at": "2026-05-12T17:29:09+00:00",
      "category": "other",
      "sentiment": "neutral",
      "signal": "watch",
      "summary": "Senate confirms Kevin Warsh to Fed board ahead of expected Chair vote",
      "tags": []
    },
    {
      "id": "e8c42bcf2fdf",
      "title": "Stablecoin yield infrastructure project raises $13.5M in round led by Sky Ecosystem",
      "source": "CoinDesk: Bitcoin, Ethereum, Crypto News and Price Data",
      "url": "https://www.coindesk.com/business/2026/05/12/stablecoin-yield-infrastructure-project-raises-usd13-5m-in-round-led-by-sky-ecosystem",
      "published_at": "2026-05-12T16:35:02+00:00",
      "category": "other",
      "sentiment": "neutral",
      "signal": "watch",
      "summary": "Stablecoin yield infrastructure project raises $13.5M in round led by Sky Ecosystem",
      "tags": []
    },
    {
      "id": "a54f0a5851e0",
      "title": "Privacy emerges as crypto’s next 'killer app,' with Arc, Canton and Tempo topping $1 billion in funding",
      "source": "CoinDesk: Bitcoin, Ethereum, Crypto News and Price Data",
      "url": "https://www.coindesk.com/business/2026/05/12/privacy-emerges-as-crypto-s-next-killer-app-with-arc-canton-and-tempo-topping-usd1-billion-in-funding",
      "published_at": "2026-05-12T16:33:42+00:00",
      "category": "other",
      "sentiment": "neutral",
      "signal": "watch",
      "summary": "Privacy emerges as crypto’s next 'killer app,' with Arc, Canton and Tempo topping $1 billion in funding",
      "tags": []
    },
    {
      "id": "50b2fefa8046",
      "title": "U.S. CFTC in talks with every major pro sports league on policing prediction markets",
      "source": "CoinDesk: Bitcoin, Ethereum, Crypto News and Price Data",
      "url": "https://www.coindesk.com/policy/2026/05/12/the-cftc-is-in-talks-with-every-major-pro-sports-league-to-crack-down-on-insider-trading",
      "published_at": "2026-05-12T15:38:56+00:00",
      "category": "other",
      "sentiment": "neutral",
      "signal": "watch",
      "summary": "U.S. CFTC in talks with every major pro sports league on policing prediction markets",
      "tags": []
    },
    {
      "id": "439185775b32",
      "title": "Bitcoin’s bull-bear cycle indicator turns green for first time since March 2023",
      "source": "CoinDesk: Bitcoin, Ethereum, Crypto News and Price Data",
      "url": "https://www.coindesk.com/markets/2026/05/12/bitcoin-s-bull-bear-cycle-turns-green-for-first-time-since-march-2023",
      "published_at": "2026-05-12T15:31:31+00:00",
      "category": "other",
      "sentiment": "neutral",
      "signal": "watch",
      "summary": "Bitcoin’s bull-bear cycle indicator turns green for first time since March 2023",
      "tags": []
    },
    {
      "id": "a7c8ef70aa95",
      "title": "Binance's chief marketing officer Rachel Conlan to leave the exchange",
      "source": "CoinDesk: Bitcoin, Ethereum, Crypto News and Price Data",
      "url": "https://www.coindesk.com/business/2026/05/12/binance-s-chief-marketing-officer-rachel-conlan-is-leaving-the-exchange",
      "published_at": "2026-05-12T15:25:46+00:00",
      "category": "other",
      "sentiment": "neutral",
      "signal": "watch",
      "summary": "Binance's chief marketing officer Rachel Conlan to leave the exchange",
      "tags": []
    },
    {
      "id": "65a8d77f60d0",
      "title": "Live markets: Bitcoin briefly falls below $80,000, as stocks tumble, yields rise on ugly inflation print",
      "source": "CoinDesk: Bitcoin, Ethereum, Crypto News and Price Data",
      "url": "https://www.coindesk.com/markets/2026/05/12/live-markets-bitcoin-holds-usd80-000-as-stocks-sink-yields-rise-on-ugly-inflation-print",
      "published_at": "2026-05-12T15:04:41+00:00",
      "category": "other",
      "sentiment": "neutral",
      "signal": "watch",
      "summary": "Live markets: Bitcoin briefly falls below $80,000, as stocks tumble, yields rise on ugly inflation print",
      "tags": []
    },
    {
      "id": "1e2885286ab8",
      "title": "Spot XRP ETFs attract biggest inflows since January",
      "source": "CoinDesk: Bitcoin, Ethereum, Crypto News and Price Data",
      "url": "https://www.coindesk.com/markets/2026/05/12/spot-xrp-etfs-attract-biggest-inflows-since-january",
      "published_at": "2026-05-12T14:08:11+00:00",
      "category": "other",
      "sentiment": "neutral",
      "signal": "watch",
      "summary": "Spot XRP ETFs attract biggest inflows since January",
      "tags": []
    },
    {
      "id": "aff8e30b8323",
      "title": "France’s central banker Beau clashes with Lagarde over private digital euro plans",
      "source": "CoinDesk: Bitcoin, Ethereum, Crypto News and Price Data",
      "url": "https://www.coindesk.com/business/2026/05/12/france-s-central-banker-beau-breaks-with-ecb-s-lagarde-calls-for-private-tokenized-euro-mobilization",
      "published_at": "2026-05-12T13:44:30+00:00",
      "category": "other",
      "sentiment": "neutral",
      "signal": "watch",
      "summary": "France’s central banker Beau clashes with Lagarde over private digital euro plans",
      "tags": []
    },
    {
      "id": "9120003cd761",
      "title": "Wall Street Lunch: EBay Rejects GameStop Takeover Proposal",
      "source": "All Articles on Seeking Alpha",
      "url": "https://seekingalpha.com/article/4903223-wall-street-lunch-ebay-rejects-gamestop-takeover-proposal?source=feed_all_articles",
      "published_at": "2026-05-12T17:32:15+00:00",
      "category": "other",
      "sentiment": "neutral",
      "signal": "watch",
      "summary": "Wall Street Lunch: EBay Rejects GameStop Takeover Proposal",
      "tags": []
    },
    {
      "id": "583e143239d9",
      "title": "Arvinas: FDA Approval Validates The Platform, But Does Not Signal Near-Term Profitability",
      "source": "All Articles on Seeking Alpha",
      "url": "https://seekingalpha.com/article/4903200-arvinas-fda-approval-validates-the-platform-but-does-not-signal-near-term-profitability?source=feed_all_articles",
      "published_at": "2026-05-12T17:31:40+00:00",
      "category": "other",
      "sentiment": "neutral",
      "signal": "watch",
      "summary": "Arvinas: FDA Approval Validates The Platform, But Does Not Signal Near-Term Profitability",
      "tags": []
    },
    {
      "id": "00f24ce8b0a7",
      "title": "Nexus Industrial REIT (NXR.UN:CA) Q1 2026 Earnings Call Transcript",
      "source": "All Articles on Seeking Alpha",
      "url": "https://seekingalpha.com/article/4903251-nexus-industrial-reit-nxr-un-ca-q1-2026-earnings-call-transcript?source=feed_all_articles",
      "published_at": "2026-05-12T17:30:55+00:00",
      "category": "other",
      "sentiment": "neutral",
      "signal": "watch",
      "summary": "Nexus Industrial REIT (NXR.UN:CA) Q1 2026 Earnings Call Transcript",
      "tags": []
    },
    {
      "id": "d1f367c4169d",
      "title": "Legend Biotech Corporation (LEGN) Q1 2026 Earnings Call Transcript",
      "source": "All Articles on Seeking Alpha",
      "url": "https://seekingalpha.com/article/4903249-legend-biotech-corporation-legn-q1-2026-earnings-call-transcript?source=feed_all_articles",
      "published_at": "2026-05-12T17:30:51+00:00",
      "category": "other",
      "sentiment": "neutral",
      "signal": "watch",
      "summary": "Legend Biotech Corporation (LEGN) Q1 2026 Earnings Call Transcript",
      "tags": []
    },
    {
      "id": "da0aefe6d648",
      "title": "Netlist, Inc. (NLST) Q1 2026 Earnings Call Transcript",
      "source": "All Articles on Seeking Alpha",
      "url": "https://seekingalpha.com/article/4903220-netlist-inc-nlst-q1-2026-earnings-call-transcript?source=feed_all_articles",
      "published_at": "2026-05-12T17:30:50+00:00",
      "category": "other",
      "sentiment": "neutral",
      "signal": "watch",
      "summary": "Netlist, Inc. (NLST) Q1 2026 Earnings Call Transcript",
      "tags": []
    },
    {
      "id": "a5cf49ec1964",
      "title": "STERIS plc (STE) Q4 2026 Earnings Call Transcript",
      "source": "All Articles on Seeking Alpha",
      "url": "https://seekingalpha.com/article/4903100-steris-plc-ste-q4-2026-earnings-call-transcript?source=feed_all_articles",
      "published_at": "2026-05-12T17:30:48+00:00",
      "category": "other",
      "sentiment": "neutral",
      "signal": "watch",
      "summary": "STERIS plc (STE) Q4 2026 Earnings Call Transcript",
      "tags": []
    },
    {
      "id": "5f471691e21c",
      "title": "Brightstar Lottery PLC (BRSL) Q1 2026 Earnings Call Transcript",
      "source": "All Articles on Seeking Alpha",
      "url": "https://seekingalpha.com/article/4903247-brightstar-lottery-plc-brsl-q1-2026-earnings-call-transcript?source=feed_all_articles",
      "published_at": "2026-05-12T17:30:46+00:00",
      "category": "other",
      "sentiment": "neutral",
      "signal": "watch",
      "summary": "Brightstar Lottery PLC (BRSL) Q1 2026 Earnings Call Transcript",
      "tags": []
    },
    {
      "id": "74e3806fdd67",
      "title": "ROKIT America Targets $25 Million U.S. IPO At High Valuation",
      "source": "All Articles on Seeking Alpha",
      "url": "https://seekingalpha.com/article/4903193-rokit-america-targets-25-million-us-ipo-at-high-valuation?source=feed_all_articles",
      "published_at": "2026-05-12T17:29:55+00:00",
      "category": "other",
      "sentiment": "neutral",
      "signal": "watch",
      "summary": "ROKIT America Targets $25 Million U.S. IPO At High Valuation",
      "tags": []
    },
    {
      "id": "4f1fbce7178b",
      "title": "Vistra: Locked Into A Virtuous Cycle",
      "source": "All Articles on Seeking Alpha",
      "url": "https://seekingalpha.com/article/4903192-vistra-stock-locked-into-a-virtuous-cycle?source=feed_all_articles",
      "published_at": "2026-05-12T17:27:40+00:00",
      "category": "other",
      "sentiment": "neutral",
      "signal": "watch",
      "summary": "Vistra: Locked Into A Virtuous Cycle",
      "tags": []
    },
    {
      "id": "6edb38e79fc5",
      "title": "Tesla: Another Chance To Sell (Technical Analysis)",
      "source": "All Articles on Seeking Alpha",
      "url": "https://seekingalpha.com/article/4903191-tesla-another-chance-to-sell-technical-analysis?source=feed_all_articles",
      "published_at": "2026-05-12T17:24:53+00:00",
      "category": "other",
      "sentiment": "neutral",
      "signal": "watch",
      "summary": "Tesla: Another Chance To Sell (Technical Analysis)",
      "tags": []
    }
  ]
}