{
  "generated_at": "2026-07-13T05:11:40.642284+00:00",
  "articles": [
    {
      "id": "3c13174d98dd",
      "title": "SK Hynix Shares Slump in Seoul After $26.5 Billion US Debut",
      "source": "Bloomberg Markets",
      "url": "https://www.bloomberg.com/news/articles/2026-07-13/sk-hynix-shares-drop-in-seoul-after-much-hyped-us-trading-debut",
      "published_at": "2026-07-13T01:27:43+00:00",
      "category": "other",
      "sentiment": "neutral",
      "signal": "watch",
      "summary": "SK Hynix Inc. shares declined in Seoul on Monday after the memory chipmaker’s highly anticipated US trading debut, with traders citing profit taking and a shift to the American depositary receipts as ",
      "tags": []
    },
    {
      "id": "a9db61d74668",
      "title": "Stocks Fall With Bonds as Iran Attacks Boost Oil: Markets Wrap",
      "source": "Bloomberg Markets",
      "url": "https://www.bloomberg.com/news/articles/2026-07-12/oil-climbs-us-futures-dip-on-fresh-iran-strikes-markets-wrap",
      "published_at": "2026-07-12T22:10:28+00:00",
      "category": "other",
      "sentiment": "neutral",
      "signal": "watch",
      "summary": "Stocks and government bonds fell as fresh US strikes on Iran pushed up oil prices and fueled bets on Federal Reserve interest-rate hikes.",
      "tags": []
    },
    {
      "id": "7d2de4662657",
      "title": "AI, Iran War Risks Weigh on Indian IT Firms’ Earnings Outlook",
      "source": "Bloomberg Markets",
      "url": "https://www.bloomberg.com/news/articles/2026-07-10/indian-it-firms-earnings-face-ai-middle-east-war-risks",
      "published_at": "2026-07-10T01:36:26+00:00",
      "category": "other",
      "sentiment": "neutral",
      "signal": "watch",
      "summary": "HCL Technologies Ltd., Wipro Ltd. and Tech Mahindra Ltd. are set to report earnings as their investor base increasingly questions the value of traditional IT services in the age of artificial intellig",
      "tags": []
    },
    {
      "id": "06edfaac7247",
      "title": "Base Metals Decline as US, Iran Flare-Up Clouds Demand Outlook",
      "source": "Bloomberg Markets",
      "url": "https://www.bloomberg.com/news/articles/2026-07-13/base-metals-decline-as-us-iran-flare-up-clouds-demand-outlook",
      "published_at": "2026-07-13T04:31:13+00:00",
      "category": "other",
      "sentiment": "neutral",
      "signal": "watch",
      "summary": "Base metals retreated after renewed hostilities between the US and Iran fueled concerns over global economic growth, clouding the outlook for industrial commodities.",
      "tags": []
    },
    {
      "id": "6917db6522d4",
      "title": "Fall of Top Graft Hunter Raises Hard Questions for Indonesia",
      "source": "Bloomberg Markets",
      "url": "https://www.bloomberg.com/news/articles/2026-07-13/gold-bars-pile-of-us-singapore-dollars-mark-fall-of-top-indonesia-graft-hunter",
      "published_at": "2026-07-13T03:36:56+00:00",
      "category": "other",
      "sentiment": "neutral",
      "signal": "watch",
      "summary": "Rows of gold bars, stacks of US and Singapore dollars and seven suitcases found inside a locked safe have become the defining images of one of the biggest scandals to hit Indonesia’s law-enforcement e",
      "tags": []
    },
    {
      "id": "7a11cb920e4c",
      "title": "El Niño and Iran War Team Up in a Food Squeeze",
      "source": "Bloomberg Markets",
      "url": "https://www.bloomberg.com/opinion/newsletters/2026-07-13/el-nino-and-iran-war-team-up-in-a-food-squeeze",
      "published_at": "2026-07-13T04:10:57+00:00",
      "category": "other",
      "sentiment": "neutral",
      "signal": "watch",
      "summary": "<p>US consumers are already on edge after prices never fell from&nbsp;post-Covid inflation.</p>",
      "tags": []
    },
    {
      "id": "020595791484",
      "title": "Gold and Silver Drop as Mideast Strikes Heighten Rate-Hike Risks",
      "source": "Bloomberg Markets",
      "url": "https://www.bloomberg.com/news/articles/2026-07-12/gold-declines-as-renewed-us-iran-strikes-raise-rate-hike-bets",
      "published_at": "2026-07-12T23:13:35+00:00",
      "category": "other",
      "sentiment": "neutral",
      "signal": "watch",
      "summary": "Gold and silver tumbled after the US and Iran exchanged fresh strikes over the weekend, sending energy prices higher and once more raising the prospects for interest-rate hikes to combat inflation.",
      "tags": []
    },
    {
      "id": "880051c31585",
      "title": "US Renews Iran Strikes as Both Sides Dispute Hormuz Status",
      "source": "Bloomberg Markets",
      "url": "https://www.bloomberg.com/news/articles/2026-07-12/us-iran-trade-wave-of-attacks-as-tehran-says-hormuz-closed",
      "published_at": "2026-07-12T08:06:08+00:00",
      "category": "other",
      "sentiment": "neutral",
      "signal": "watch",
      "summary": "The US launched fresh missile attacks against Iran on Sunday in what has become a pattern of strikes and counterstrikes by Washington and Tehran as the two sides issued conflicting declarations over w",
      "tags": []
    },
    {
      "id": "12d793a4a56d",
      "title": "Modi Seals Deals After Courting Indo-Pacific Partners",
      "source": "Bloomberg Markets",
      "url": "https://www.bloomberg.com/news/videos/2026-07-13/modi-seals-deals-after-courting-indo-pacific-partners-video",
      "published_at": "2026-07-13T03:29:03+00:00",
      "category": "other",
      "sentiment": "neutral",
      "signal": "watch",
      "summary": "Prime Minister Narendra Modi used a three-nation tour to deepen India’s Indo-Pacific partnerships, Bloomberg's Swati Pandey reports. (Source: Bloomberg)",
      "tags": []
    },
    {
      "id": "b643f8a811a2",
      "title": "MiniMax Shares Slump After JPMorgan Cuts Target Price Further",
      "source": "Bloomberg Markets",
      "url": "https://www.bloomberg.com/news/articles/2026-07-13/minimax-shares-slump-after-jpmorgan-cuts-target-price-further",
      "published_at": "2026-07-13T03:23:30+00:00",
      "category": "other",
      "sentiment": "neutral",
      "signal": "watch",
      "summary": "MiniMax Group Inc.’s shares plunged, after JPMorgan Chase &amp; Co. slashed the Chinese AI model maker’s price target for the second time in less than a week on value dilution concerns caused by fresh",
      "tags": []
    },
    {
      "id": "6c3eb395e64a",
      "title": "US launches more strikes on Iran as ceasefire teeters",
      "source": "International homepage",
      "url": "https://www.ft.com/content/c5beec47-ba53-412e-910e-6b9ab2f3238d",
      "published_at": "2026-07-13T04:28:25+00:00",
      "category": "other",
      "sentiment": "neutral",
      "signal": "watch",
      "summary": "Fighting escalates as Trump insists Strait of Hormuz remains open while Tehran says it is closed",
      "tags": []
    },
    {
      "id": "0e93c8262da3",
      "title": "Oil prices jump as US and Iran step up tit-for-tat strikes",
      "source": "International homepage",
      "url": "https://www.ft.com/content/a3075fc2-74bd-4908-ab02-bbac79c32ee6",
      "published_at": "2026-07-12T22:41:05+00:00",
      "category": "other",
      "sentiment": "neutral",
      "signal": "watch",
      "summary": "Traders fear escalating hostilities could further restrict the flow of crude through the Strait of Hormuz",
      "tags": []
    },
    {
      "id": "3304782d0f2e",
      "title": "Iran bets Trump will blink first",
      "source": "International homepage",
      "url": "https://www.ft.com/content/5bcb587a-e74a-4a34-9d18-c52520bd7b05",
      "published_at": "2026-07-12T17:57:12+00:00",
      "category": "other",
      "sentiment": "neutral",
      "signal": "watch",
      "summary": "Tehran takes high-stakes gamble with US over Strait of Hormuz",
      "tags": []
    },
    {
      "id": "82d13f719d8e",
      "title": "Jane Fraser’s ruthless remake of Citigroup",
      "source": "International homepage",
      "url": "https://www.ft.com/content/632c0f53-66f2-4c7d-8e4f-bae514cef713",
      "published_at": "2026-07-13T04:00:05+00:00",
      "category": "other",
      "sentiment": "neutral",
      "signal": "watch",
      "summary": "The bank has sold assets, cut jobs and made controversial new hires while cultivating a closer relationship with Trump. Is it enough to get back into the big time?",
      "tags": []
    },
    {
      "id": "f2cd549afb05",
      "title": "‘Trump accounts’ and how to spread America’s wealth",
      "source": "International homepage",
      "url": "https://www.ft.com/content/f98d880c-6e7f-486c-8336-4a26186a5955",
      "published_at": "2026-07-13T04:00:21+00:00",
      "category": "other",
      "sentiment": "neutral",
      "signal": "watch",
      "summary": "Political stability in the US requires it — the question is, pre-distribution or redistribution?",
      "tags": []
    },
    {
      "id": "0ee30f861611",
      "title": "AI is not enough to arrest China’s decline",
      "source": "International homepage",
      "url": "https://www.ft.com/content/0dbbef33-059b-4ec9-b504-31f37a0c4053",
      "published_at": "2026-07-13T04:00:18+00:00",
      "category": "other",
      "sentiment": "neutral",
      "signal": "watch",
      "summary": "There are other, more powerful forces weighing on the country’s economy",
      "tags": []
    },
    {
      "id": "18310173ed87",
      "title": "Wall Street feasts on fees from SpaceX IPO and mega-mergers",
      "source": "International homepage",
      "url": "https://www.ft.com/content/98207dc6-4deb-47c4-bbc6-8b1dd6c3b18c",
      "published_at": "2026-07-13T04:00:20+00:00",
      "category": "other",
      "sentiment": "neutral",
      "signal": "watch",
      "summary": "Top US banks benefit from revival of large deals as AI optimism and strong consumer fuel market rally",
      "tags": []
    },
    {
      "id": "718bbbc73284",
      "title": "Companies turn to Chinese AI models to cut costs",
      "source": "International homepage",
      "url": "https://www.ft.com/content/9c8ff45b-7c20-4c2e-93c9-c52339ffdcee",
      "published_at": "2026-07-13T04:00:17+00:00",
      "category": "other",
      "sentiment": "neutral",
      "signal": "watch",
      "summary": "DoorDash, Siemens and Airbnb are among those seeking to curb ballooning bills and reduce reliance on US technology",
      "tags": []
    },
    {
      "id": "a45cdaf0752e",
      "title": "Dimon pressed over whether he lobbied UK government on Epstein’s advice",
      "source": "International homepage",
      "url": "https://www.ft.com/content/4f4940cb-5ab4-4c65-bb2c-1503ed4734c1",
      "published_at": "2026-07-13T04:01:02+00:00",
      "category": "other",
      "sentiment": "neutral",
      "signal": "watch",
      "summary": "US Senator Elizabeth Warren demands JPMorgan boss explain any links with paedophile over proposed tax on bankers’ bonuses",
      "tags": []
    },
    {
      "id": "57a01570d6a4",
      "title": "EU buys record amount of gas from Russia’s flagship plant",
      "source": "International homepage",
      "url": "https://www.ft.com/content/de9bbc3a-c317-4e5f-a324-6ec0dde45722",
      "published_at": "2026-07-13T03:00:02+00:00",
      "category": "other",
      "sentiment": "neutral",
      "signal": "watch",
      "summary": "Europe purchased almost all the LNG produced by the Yamal facility in the first half of 2026 ahead of import ban",
      "tags": []
    },
    {
      "id": "2f031740b320",
      "title": "Bank of Thailand targets USDT and cash flows in gray money crackdown",
      "source": "Cointelegraph.com News",
      "url": "https://cointelegraph.com/news/thailand-targets-stablecoins-in-latest-laundering-crackdown?utm_source=rss_feed&utm_medium=rss&utm_campaign=rss_partner_inbound",
      "published_at": "2026-07-13T04:43:50+00:00",
      "category": "other",
      "sentiment": "neutral",
      "signal": "watch",
      "summary": "<p style=\"float: right; margin: 0 0 10px 15px; width: 240px;\"><img alt=\"Bank of Thailand targets USDT and cash flows in gray money crackdown\" class=\"type:primaryImage\" src=\"https://s3-images.ctmedia.i",
      "tags": []
    },
    {
      "id": "bbe5e6c8e53c",
      "title": "Bitcoin ETFs draw $197M, snap 8-week outflow streak",
      "source": "Cointelegraph.com News",
      "url": "https://cointelegraph.com/news/bitcoin-etfs-draw-197m-snap-8-week-outflow-streak?utm_source=rss_feed&utm_medium=rss&utm_campaign=rss_partner_inbound",
      "published_at": "2026-07-13T01:49:17+00:00",
      "category": "other",
      "sentiment": "neutral",
      "signal": "watch",
      "summary": "<p style=\"float: right; margin: 0 0 10px 15px; width: 240px;\"><img alt=\"Bitcoin ETFs draw $197M, snap 8-week outflow streak\" class=\"type:primaryImage\" src=\"https://s3-images.ctmedia.io/media/article-c",
      "tags": []
    },
    {
      "id": "03b04ebefa0e",
      "title": "Robinhood L2 sparks ETH optimism, Saylor 'muddies waters.' Hodler's Digest, July 5-12, 2026",
      "source": "Cointelegraph.com News",
      "url": "https://cointelegraph.com/features/ethereum-climbs-as-robinhood-l2-takes-off?utm_source=rss_feed&utm_medium=rss&utm_campaign=rss_partner_inbound",
      "published_at": "2026-07-12T23:24:26+00:00",
      "category": "other",
      "sentiment": "neutral",
      "signal": "watch",
      "summary": "<p style=\"float: right; margin: 0 0 10px 15px; width: 240px;\"><img alt=\"Robinhood L2 sparks ETH optimism, Saylor 'muddies waters.' Hodler's Digest, July 5-12, 2026\" class=\"type:primaryImage\" src=\"http",
      "tags": []
    },
    {
      "id": "5f7923844b65",
      "title": "Strategy's Saylor needs clarity in BTC pivot message to convince investors: StanChart",
      "source": "Cointelegraph.com News",
      "url": "https://cointelegraph.com/news/strategys-saylor-needs-clarity-in-btc-pivot-message-to-convince-investors-stanchart?utm_source=rss_feed&utm_medium=rss&utm_campaign=rss_partner_inbound",
      "published_at": "2026-07-12T18:16:45+00:00",
      "category": "other",
      "sentiment": "neutral",
      "signal": "watch",
      "summary": "<p style=\"float: right; margin: 0 0 10px 15px; width: 240px;\"><img alt=\"Strategy's Saylor needs clarity in BTC pivot message to convince investors: StanChart\" class=\"type:primaryImage\" src=\"https://s3",
      "tags": []
    },
    {
      "id": "f41e68c2f311",
      "title": "Pakistan crypto chief seeks dialogue after scholar rules against crypto payments",
      "source": "Cointelegraph.com News",
      "url": "https://cointelegraph.com/news/pakistan-crypto-chief-dialogue-islamic-ruling?utm_source=rss_feed&utm_medium=rss&utm_campaign=rss_partner_inbound",
      "published_at": "2026-07-12T12:26:09+00:00",
      "category": "other",
      "sentiment": "neutral",
      "signal": "watch",
      "summary": "<p style=\"float: right; margin: 0 0 10px 15px; width: 240px;\"><img alt=\"Pakistan crypto chief seeks dialogue after scholar rules against crypto payments\" class=\"type:primaryImage\" src=\"https://s3-imag",
      "tags": []
    },
    {
      "id": "b4c4fcf49830",
      "title": "Cambridge study puts Ethereum near the lower end of PoS energy intensity",
      "source": "Cointelegraph.com News",
      "url": "https://cointelegraph.com/news/ethereum-pos-energy-intensity-cambridge-study?utm_source=rss_feed&utm_medium=rss&utm_campaign=rss_partner_inbound",
      "published_at": "2026-07-12T09:29:00+00:00",
      "category": "other",
      "sentiment": "neutral",
      "signal": "watch",
      "summary": "<p style=\"float: right; margin: 0 0 10px 15px; width: 240px;\"><img alt=\"Cambridge study puts Ethereum near the lower end of PoS energy intensity\" class=\"type:primaryImage\" src=\"https://s3-images.ctmed",
      "tags": []
    },
    {
      "id": "c3e39645c5a8",
      "title": "Bitcoin bulls Michael Saylor, Adam Back slam BIP-110 Ordinals proposal",
      "source": "Cointelegraph.com News",
      "url": "https://cointelegraph.com/news/bitcoin-leaders-michael-saylor-and-adam-back-rebuff-bip-110-proposal?utm_source=rss_feed&utm_medium=rss&utm_campaign=rss_partner_inbound",
      "published_at": "2026-07-12T04:28:00+00:00",
      "category": "other",
      "sentiment": "neutral",
      "signal": "watch",
      "summary": "<p style=\"float: right; margin: 0 0 10px 15px; width: 240px;\"><img alt=\"Bitcoin bulls Michael Saylor, Adam Back slam BIP-110 Ordinals proposal\" class=\"type:primaryImage\" src=\"https://s3-images.ctmedia",
      "tags": []
    },
    {
      "id": "78f7a83e386d",
      "title": "Here’s what happened in crypto today",
      "source": "Cointelegraph.com News",
      "url": "https://cointelegraph.com/news/what-happened-in-crypto-today?utm_source=rss_feed&utm_medium=rss&utm_campaign=rss_partner_inbound",
      "published_at": "2026-07-12T04:24:58+00:00",
      "category": "other",
      "sentiment": "neutral",
      "signal": "watch",
      "summary": "<p style=\"float: right; margin: 0 0 10px 15px; width: 240px;\"><img alt=\"Here’s what happened in crypto today\" class=\"type:primaryImage\" src=\"https://s3-images.ctmedia.io/media/article-covers/article-c",
      "tags": []
    },
    {
      "id": "a0bdb2fcabac",
      "title": "Empery Digital shares rise after selling BTC to fund AI data center project",
      "source": "Cointelegraph.com News",
      "url": "https://cointelegraph.com/news/empery-digital-shares-rise-after-selling-bitcoin-treasury-to-fund-ai-data-center-project?utm_source=rss_feed&utm_medium=rss&utm_campaign=rss_partner_inbound",
      "published_at": "2026-07-12T01:05:00+00:00",
      "category": "other",
      "sentiment": "neutral",
      "signal": "watch",
      "summary": "<p style=\"float: right; margin: 0 0 10px 15px; width: 240px;\"><img alt=\"Empery Digital shares rise after selling BTC to fund AI data center project\" class=\"type:primaryImage\" src=\"https://s3-images.ct",
      "tags": []
    },
    {
      "id": "672f1d23c0ed",
      "title": "Bitcoin nearing late stages of bear market: Jamie Coutts, Real Vision",
      "source": "Cointelegraph.com News",
      "url": "https://cointelegraph.com/features/bitcoin-is-approaching-the-second-half-of-the-bear-market-jamie-coutts?utm_source=rss_feed&utm_medium=rss&utm_campaign=rss_partner_inbound",
      "published_at": "2026-07-11T13:30:00+00:00",
      "category": "other",
      "sentiment": "neutral",
      "signal": "watch",
      "summary": "<p style=\"float: right; margin: 0 0 10px 15px; width: 240px;\"><img alt=\"Bitcoin nearing late stages of bear market: Jamie Coutts, Real Vision\" class=\"type:primaryImage\" src=\"https://s3-images.ctmedia.",
      "tags": []
    },
    {
      "id": "f43639b83082",
      "title": "Bitcoin holds near $63,800 as war-driven selloff hits everything but crypto",
      "source": "CoinDesk: Bitcoin, Ethereum, Crypto News and Price Data",
      "url": "https://www.coindesk.com/markets/2026/07/13/bitcoin-holds-near-usd63-800-as-war-driven-selloff-hits-everything-but-crypto",
      "published_at": "2026-07-13T04:48:11+00:00",
      "category": "other",
      "sentiment": "neutral",
      "signal": "watch",
      "summary": "Bitcoin holds near $63,800 as war-driven selloff hits everything but crypto",
      "tags": []
    },
    {
      "id": "81a903f2e18b",
      "title": "Signs of life?: State of Crypto",
      "source": "CoinDesk: Bitcoin, Ethereum, Crypto News and Price Data",
      "url": "https://www.coindesk.com/policy/2026/07/12/signs-of-life-state-of-crypto",
      "published_at": "2026-07-12T18:30:00+00:00",
      "category": "other",
      "sentiment": "neutral",
      "signal": "watch",
      "summary": "Signs of life?: State of Crypto",
      "tags": []
    },
    {
      "id": "f28a4f4c3ff0",
      "title": "Stablecoin market cap has shrunk by $10 billion since May, but analyst sees no reason to panic",
      "source": "CoinDesk: Bitcoin, Ethereum, Crypto News and Price Data",
      "url": "https://www.coindesk.com/markets/2026/07/12/stablecoin-market-cap-has-shrunk-by-usd10-billion-since-may-but-analyst-sees-no-reason-to-panic",
      "published_at": "2026-07-12T13:00:00+00:00",
      "category": "other",
      "sentiment": "neutral",
      "signal": "watch",
      "summary": "Stablecoin market cap has shrunk by $10 billion since May, but analyst sees no reason to panic",
      "tags": []
    },
    {
      "id": "612c476146f8",
      "title": "Bitcoin is nearing a power law support line Fidelity has tracked since 2015",
      "source": "CoinDesk: Bitcoin, Ethereum, Crypto News and Price Data",
      "url": "https://www.coindesk.com/markets/2026/07/12/bitcoin-is-nearing-a-power-law-support-line-fidelity-has-tracked-since-2015",
      "published_at": "2026-07-12T11:30:00+00:00",
      "category": "other",
      "sentiment": "neutral",
      "signal": "watch",
      "summary": "Bitcoin is nearing a power law support line Fidelity has tracked since 2015",
      "tags": []
    },
    {
      "id": "18e3b43b6ea5",
      "title": "Bitcoin, ether little changed as U.S. launches fresh Iran strikes",
      "source": "CoinDesk: Bitcoin, Ethereum, Crypto News and Price Data",
      "url": "https://www.coindesk.com/markets/2026/07/12/bitcoin-ether-little-changed-as-u-s-launches-fresh-iran-strikes",
      "published_at": "2026-07-12T06:18:15+00:00",
      "category": "other",
      "sentiment": "neutral",
      "signal": "watch",
      "summary": "Bitcoin, ether little changed as U.S. launches fresh Iran strikes",
      "tags": []
    },
    {
      "id": "ddbdb5387fa6",
      "title": "Ripple once weighed shutting down and handing XRP to shareholders, CEO says",
      "source": "CoinDesk: Bitcoin, Ethereum, Crypto News and Price Data",
      "url": "https://www.coindesk.com/markets/2026/07/12/ripple-once-weighed-shutting-down-and-handing-xrp-to-shareholders-ceo-says",
      "published_at": "2026-07-12T06:09:49+00:00",
      "category": "other",
      "sentiment": "neutral",
      "signal": "watch",
      "summary": "Ripple once weighed shutting down and handing XRP to shareholders, CEO says",
      "tags": []
    },
    {
      "id": "1712bdf6957e",
      "title": "Bitcoin’s BIP 110 fork deadline nears with miner support at zero",
      "source": "CoinDesk: Bitcoin, Ethereum, Crypto News and Price Data",
      "url": "https://www.coindesk.com/tech/2026/07/12/bitcoin-s-bip-110-fork-deadline-nears-with-miner-support-at-zero",
      "published_at": "2026-07-12T05:49:52+00:00",
      "category": "other",
      "sentiment": "neutral",
      "signal": "watch",
      "summary": "Bitcoin’s BIP 110 fork deadline nears with miner support at zero",
      "tags": []
    },
    {
      "id": "b3d6af79e7c4",
      "title": "Lending protocol Bonzo loses 77% of value locked as $9 million oracle exploit rattles Hedera",
      "source": "CoinDesk: Bitcoin, Ethereum, Crypto News and Price Data",
      "url": "https://www.coindesk.com/web3/2026/07/11/lending-protocol-bonzo-loses-77-of-value-locked-as-usd9-million-oracle-exploit-rattles-hedera",
      "published_at": "2026-07-11T18:06:58+00:00",
      "category": "other",
      "sentiment": "neutral",
      "signal": "watch",
      "summary": "Lending protocol Bonzo loses 77% of value locked as $9 million oracle exploit rattles Hedera",
      "tags": []
    },
    {
      "id": "70ffd02fce70",
      "title": "Crypto IPO market stalls as capital rotates to AI and macro uncertainty weighs",
      "source": "CoinDesk: Bitcoin, Ethereum, Crypto News and Price Data",
      "url": "https://www.coindesk.com/business/2026/07/08/crypto-ipo-market-stalls-as-capital-rotates-to-ai-and-macro-uncertainty-weighs",
      "published_at": "2026-07-11T17:07:24+00:00",
      "category": "other",
      "sentiment": "neutral",
      "signal": "watch",
      "summary": "Crypto IPO market stalls as capital rotates to AI and macro uncertainty weighs",
      "tags": []
    },
    {
      "id": "9a6a763590d6",
      "title": "The UK has finally shown it’s serious about crypto",
      "source": "CoinDesk: Bitcoin, Ethereum, Crypto News and Price Data",
      "url": "https://www.coindesk.com/opinion/2026/07/11/the-uk-has-finally-shown-it-s-serious-about-crypto",
      "published_at": "2026-07-11T15:00:00+00:00",
      "category": "other",
      "sentiment": "neutral",
      "signal": "watch",
      "summary": "The UK has finally shown it’s serious about crypto",
      "tags": []
    },
    {
      "id": "bed21a52a26f",
      "title": "AVDV: The Commodity Engine Has Cooled, Japan Hasn't",
      "source": "All Articles on Seeking Alpha",
      "url": "https://seekingalpha.com/article/4921473-avdv-the-commodity-engine-has-cooled-japan-hasnt-downgrade-hold?source=feed_all_articles",
      "published_at": "2026-07-13T05:00:16+00:00",
      "category": "other",
      "sentiment": "neutral",
      "signal": "watch",
      "summary": "AVDV: The Commodity Engine Has Cooled, Japan Hasn't",
      "tags": []
    },
    {
      "id": "7f2f29f15dc5",
      "title": "Nextdoor: Building An AI Business That Big Companies Can't Copy",
      "source": "All Articles on Seeking Alpha",
      "url": "https://seekingalpha.com/article/4921472-nextdoor-stock-ai-business-big-companies-cant-copy?source=feed_all_articles",
      "published_at": "2026-07-13T04:37:47+00:00",
      "category": "other",
      "sentiment": "neutral",
      "signal": "watch",
      "summary": "Nextdoor: Building An AI Business That Big Companies Can't Copy",
      "tags": []
    },
    {
      "id": "e439b00c8477",
      "title": "EUSA: Take Profits (Rating Downgrade)",
      "source": "All Articles on Seeking Alpha",
      "url": "https://seekingalpha.com/article/4921471-eusa-take-profits-on-etf?source=feed_all_articles",
      "published_at": "2026-07-13T04:26:13+00:00",
      "category": "other",
      "sentiment": "neutral",
      "signal": "watch",
      "summary": "EUSA: Take Profits (Rating Downgrade)",
      "tags": []
    },
    {
      "id": "944356913ae1",
      "title": "Politics And The Markets 07/13/26",
      "source": "All Articles on Seeking Alpha",
      "url": "https://seekingalpha.com/article/4919376-politics-and-the-markets-071326?source=feed_all_articles",
      "published_at": "2026-07-13T04:00:00+00:00",
      "category": "other",
      "sentiment": "neutral",
      "signal": "watch",
      "summary": "Politics And The Markets 07/13/26",
      "tags": []
    },
    {
      "id": "ac7d2f117b5f",
      "title": "XPeng: Strong June Deliveries Create Upside",
      "source": "All Articles on Seeking Alpha",
      "url": "https://seekingalpha.com/article/4921469-xpeng-strong-june-deliveries-create-upside?source=feed_all_articles",
      "published_at": "2026-07-13T03:39:58+00:00",
      "category": "other",
      "sentiment": "neutral",
      "signal": "watch",
      "summary": "XPeng: Strong June Deliveries Create Upside",
      "tags": []
    },
    {
      "id": "973a1bc5f3f1",
      "title": "CHW: The Discount Is Attractive, But The Strategy Isn't Working (Rating Downgrade)",
      "source": "All Articles on Seeking Alpha",
      "url": "https://seekingalpha.com/article/4921466-chw-cef-discount-attractive-strategy-not-working-rating-downgrade?source=feed_all_articles",
      "published_at": "2026-07-13T02:44:54+00:00",
      "category": "other",
      "sentiment": "neutral",
      "signal": "watch",
      "summary": "CHW: The Discount Is Attractive, But The Strategy Isn't Working (Rating Downgrade)",
      "tags": []
    },
    {
      "id": "092d708350e3",
      "title": "Alliance Resource Partners: More Than Coal As AI Fuels The Pivot",
      "source": "All Articles on Seeking Alpha",
      "url": "https://seekingalpha.com/article/4921465-alliance-resource-partners-stock-more-than-coal-as-ai-fuels-pivot?source=feed_all_articles",
      "published_at": "2026-07-13T02:09:42+00:00",
      "category": "other",
      "sentiment": "neutral",
      "signal": "watch",
      "summary": "Alliance Resource Partners: More Than Coal As AI Fuels The Pivot",
      "tags": []
    },
    {
      "id": "5da1590af9e6",
      "title": "Reviewing Recent Picks: Winners, Laggards, And Lessons From SpaceX, Meta, Micron, Bloom, And Credo",
      "source": "All Articles on Seeking Alpha",
      "url": "https://seekingalpha.com/article/4921464-reviewing-recent-picks-winners-laggards-lessons-spacex-meta-micron-bloom-credo-success-or-failure?source=feed_all_articles",
      "published_at": "2026-07-13T01:30:48+00:00",
      "category": "other",
      "sentiment": "neutral",
      "signal": "watch",
      "summary": "Reviewing Recent Picks: Winners, Laggards, And Lessons From SpaceX, Meta, Micron, Bloom, And Credo",
      "tags": []
    },
    {
      "id": "8a4e421f9d41",
      "title": "Ponce Financial Group Remains Compelling Even After Its Impressive Rise",
      "source": "All Articles on Seeking Alpha",
      "url": "https://seekingalpha.com/article/4921461-ponce-financial-group-remains-compelling-even-after-its-impressive-rise?source=feed_all_articles",
      "published_at": "2026-07-13T01:30:00+00:00",
      "category": "other",
      "sentiment": "neutral",
      "signal": "watch",
      "summary": "Ponce Financial Group Remains Compelling Even After Its Impressive Rise",
      "tags": []
    },
    {
      "id": "e262dbaf4987",
      "title": "Canadian Natural Resources: A Dividend Machine In A Volatile Oil Market",
      "source": "All Articles on Seeking Alpha",
      "url": "https://seekingalpha.com/article/4921460-canadian-natural-resources-dividend-machine-in-a-volatile-oil-market?source=feed_all_articles",
      "published_at": "2026-07-13T01:10:00+00:00",
      "category": "other",
      "sentiment": "neutral",
      "signal": "watch",
      "summary": "Canadian Natural Resources: A Dividend Machine In A Volatile Oil Market",
      "tags": []
    }
  ]
}