{
  "generated_at": "2026-07-23T16:32:58.357513+00:00",
  "articles": [
    {
      "id": "50dfed9e578e",
      "title": "Latest Oil Market News and Analysis for July 23",
      "source": "Bloomberg Markets",
      "url": "https://www.bloomberg.com/news/articles/2026-07-22/latest-oil-market-news-and-analysis-for-july-23",
      "published_at": "2026-07-22T22:02:06+00:00",
      "category": "other",
      "sentiment": "neutral",
      "signal": "watch",
      "summary": "Oil surged past $100 a barrel for the first time in two months after Iran-backed Houthi militants said they attacked two Saudi Arabian tankers in the Red Sea, escalating the Middle East conflict and t",
      "tags": []
    },
    {
      "id": "248bcf91d681",
      "title": "BlackRock’s GIP Eyes Bundling Fund Stakes in Securitization Deal",
      "source": "Bloomberg Markets",
      "url": "https://www.bloomberg.com/news/articles/2026-07-23/blackrock-s-gip-eyes-bundling-fund-stakes-in-securitization-deal",
      "published_at": "2026-07-23T16:03:55+00:00",
      "category": "other",
      "sentiment": "neutral",
      "signal": "watch",
      "summary": "BlackRock Inc.’s Global Infrastructure Partners LP has been in discussions with investors to sell bonds backed by stakes in some of its private capital funds, joining a growing list of asset managers ",
      "tags": []
    },
    {
      "id": "70e8669502de",
      "title": "Stocks Hit by AI and War Jitters as Oil Tops $100: Markets Wrap",
      "source": "Bloomberg Markets",
      "url": "https://www.bloomberg.com/news/articles/2026-07-22/stock-market-today-dow-s-p-live-updates",
      "published_at": "2026-07-22T22:12:30+00:00",
      "category": "other",
      "sentiment": "neutral",
      "signal": "watch",
      "summary": "A surge in oil spurred by the escalating Iran war sent stocks and bonds lower, with Wall Street also rattled by renewed concerns over whether massive artificial-intelligence investments will pay off.",
      "tags": []
    },
    {
      "id": "16a7cb481b4b",
      "title": "NYC’s Former HSBC Tower Seeks More Than $800 Million in Sale",
      "source": "Bloomberg Markets",
      "url": "https://www.bloomberg.com/news/articles/2026-07-23/nyc-s-former-hsbc-tower-seeks-more-than-800-million-in-sale",
      "published_at": "2026-07-23T15:44:51+00:00",
      "category": "other",
      "sentiment": "neutral",
      "signal": "watch",
      "summary": "A Manhattan office tower where Amazon.com Inc. has offices is going up for sale.",
      "tags": []
    },
    {
      "id": "eda3413b3b2d",
      "title": "Bund Yields Hit 15-Year High as $100 Oil Fans Inflation Concerns",
      "source": "Bloomberg Markets",
      "url": "https://www.bloomberg.com/news/articles/2026-07-23/german-bond-yields-hit-15-year-as-oil-prices-spike-before-ecb",
      "published_at": "2026-07-23T08:03:27+00:00",
      "category": "other",
      "sentiment": "neutral",
      "signal": "watch",
      "summary": "German bond yields rose to the highest level since 2011 as surging oil prices prompted bigger bets on interest-rate hikes, even as the European Central Bank kept its benchmark unchanged.",
      "tags": []
    },
    {
      "id": "4aa6cef6fbcb",
      "title": "Nasdaq 100 Eyes Worst Day in Month as Oil Prices Soar Over $100",
      "source": "Bloomberg Markets",
      "url": "https://www.bloomberg.com/news/articles/2026-07-23/us-stock-futures-drop-as-traders-focus-on-ai-spending-oil-jumps",
      "published_at": "2026-07-23T12:09:56+00:00",
      "category": "other",
      "sentiment": "neutral",
      "signal": "watch",
      "summary": "The Nasdaq 100 Index tumbled, putting it on track for its worst day in a month, as doubts about the payoffs from debt-fueled artificial-intelligence spending boom dragged down big tech stocks. Oil pri",
      "tags": []
    },
    {
      "id": "c85d24259134",
      "title": "Chocolate Maker Lindt Faces US Lawsuit Over Child Labor Allegations",
      "source": "Bloomberg Markets",
      "url": "https://www.bloomberg.com/news/articles/2026-07-23/chocolate-maker-lindt-faces-us-suit-over-child-labor-allegations",
      "published_at": "2026-07-23T15:36:05+00:00",
      "category": "other",
      "sentiment": "neutral",
      "signal": "watch",
      "summary": "Lindt &amp; Spruengli AG has been sued by an activist law firm in the US which alleges the Swiss chocolate maker is falsely promoting its efforts to battle child labor in Ghana and the Ivory Coast fro",
      "tags": []
    },
    {
      "id": "51d84892c2bd",
      "title": "How Leveraged Exchange-Traded Funds Are Suddenly Everywhere",
      "source": "Bloomberg Markets",
      "url": "https://www.bloomberg.com/news/articles/2026-07-23/how-leveraged-exchange-traded-funds-are-suddenly-everywhere",
      "published_at": "2026-07-23T15:30:18+00:00",
      "category": "other",
      "sentiment": "neutral",
      "signal": "watch",
      "summary": "<p>On this episode of&nbsp;<em>Trillions</em>, we discuss what’s fueling the boom&nbsp;and how these exchange-traded funds work in today’s market.</p>",
      "tags": []
    },
    {
      "id": "eefdb0d52252",
      "title": "Russia’s Black Sea Waters Not Safe for Ships Amid Attacks",
      "source": "Bloomberg Markets",
      "url": "https://www.bloomberg.com/news/articles/2026-07-23/russia-says-its-black-sea-waters-not-safe-for-ships-amid-attacks",
      "published_at": "2026-07-23T14:26:36+00:00",
      "category": "other",
      "sentiment": "neutral",
      "signal": "watch",
      "summary": "Moscow warned that it is unsafe to navigate in its Black Sea waters after Ukraine has been ramping up attacks on Russia-linked ships in the area.",
      "tags": []
    },
    {
      "id": "95758a0398d6",
      "title": "The Worrying Signal Embedded in the Momentum Selloff",
      "source": "Bloomberg Markets",
      "url": "https://www.bloomberg.com/news/newsletters/2026-07-23/the-worrying-signal-embedded-in-the-momentum-selloff",
      "published_at": "2026-07-23T15:10:31+00:00",
      "category": "other",
      "sentiment": "neutral",
      "signal": "watch",
      "summary": "A loss of market leadership.",
      "tags": []
    },
    {
      "id": "68fa0f98bb52",
      "title": "Oil hits $100 for first time since May while US stocks slide",
      "source": "International homepage",
      "url": "https://www.ft.com/content/3fd494d1-ee74-4c0f-9cd6-34e2283961df?syn-25a6b1a6=1",
      "published_at": "2026-07-23T16:08:49+00:00",
      "category": "other",
      "sentiment": "neutral",
      "signal": "watch",
      "summary": "Donald Trump warns US is weighing ‘massive attack’ on Iran as Middle East tensions ratchet higher",
      "tags": []
    },
    {
      "id": "90cfabe3a1cd",
      "title": "Houthi attacks threaten Saudi Arabia’s oil lifeline",
      "source": "International homepage",
      "url": "https://www.ft.com/content/02bf3e4d-7719-4482-9f2b-ab14bd3fe9c3?syn-25a6b1a6=1",
      "published_at": "2026-07-23T09:51:03+00:00",
      "category": "other",
      "sentiment": "neutral",
      "signal": "watch",
      "summary": "Asian refiners may wait an extra month for crude as tankers abandon the route through Bab al-Mandab",
      "tags": []
    },
    {
      "id": "9564ac805fe9",
      "title": "Oil price surge drives global bond sell-off",
      "source": "International homepage",
      "url": "https://www.ft.com/content/66bf810f-c1c0-488d-bd02-f8eba3acd743?syn-25a6b1a6=1",
      "published_at": "2026-07-23T14:24:01+00:00",
      "category": "other",
      "sentiment": "neutral",
      "signal": "watch",
      "summary": "Brent crude’s rise above $100 threatens a prolonged surge in inflation and resetting interest rate expectations",
      "tags": []
    },
    {
      "id": "37d7ac6715b1",
      "title": "Japan awakes",
      "source": "International homepage",
      "url": "https://www.ft.com/content/397c04d8-db0f-4902-9ea0-269584f43697?syn-25a6b1a6=1",
      "published_at": "2026-07-23T04:00:21+00:00",
      "category": "other",
      "sentiment": "neutral",
      "signal": "watch",
      "summary": "Why 1 per cent interest rates could shake everything up after a generation of deflation",
      "tags": []
    },
    {
      "id": "8496f41d75d7",
      "title": "Is Trump winning the tariff wars?",
      "source": "International homepage",
      "url": "https://www.ft.com/content/7b53032e-894d-43ac-9dd1-2b94572b8489?syn-25a6b1a6=1",
      "published_at": "2026-07-23T04:00:12+00:00",
      "category": "other",
      "sentiment": "neutral",
      "signal": "watch",
      "summary": "Time to tot up the scores",
      "tags": []
    },
    {
      "id": "e2fe335e51db",
      "title": "Why the US is losing Chinese AI stars",
      "source": "International homepage",
      "url": "https://www.ft.com/content/0c773366-61a2-4d33-894e-6b3ddfcfd9b3?syn-25a6b1a6=1",
      "published_at": "2026-07-22T23:01:08+00:00",
      "category": "other",
      "sentiment": "neutral",
      "signal": "watch",
      "summary": "More entrepreneurs from China believe there are now greater opportunities at home than in Silicon Valley",
      "tags": []
    },
    {
      "id": "9a70c29314de",
      "title": "EU fines Google €890mn in test of Trump’s threats to protect Big Tech",
      "source": "International homepage",
      "url": "https://www.ft.com/content/c836e73b-66bb-4aa1-b85b-dd5b6eb89af0?syn-25a6b1a6=1",
      "published_at": "2026-07-23T10:00:08+00:00",
      "category": "other",
      "sentiment": "neutral",
      "signal": "watch",
      "summary": "EU competition chief says it is bloc’s ‘duty to defend rule of law’ while delivering ‘strong message’ to search giant",
      "tags": []
    },
    {
      "id": "952251e486d6",
      "title": "Google burns through $6bn in cash as AI spending climbs again",
      "source": "International homepage",
      "url": "https://www.ft.com/content/b02f972c-c764-4006-9377-42563d9d5530?syn-25a6b1a6=1",
      "published_at": "2026-07-22T22:39:24+00:00",
      "category": "other",
      "sentiment": "neutral",
      "signal": "watch",
      "summary": "Search giant says it will commit up to $205bn to AI investments in 2026",
      "tags": []
    },
    {
      "id": "f3c4acbd7cf6",
      "title": "Trump Media fast feed for president’s posts sparks Wall Street backlash",
      "source": "International homepage",
      "url": "https://www.ft.com/content/019ce313-00c5-4d7d-a26c-acd7250de84a?syn-25a6b1a6=1",
      "published_at": "2026-07-23T04:00:21+00:00",
      "category": "other",
      "sentiment": "neutral",
      "signal": "watch",
      "summary": "New venture has raised questions as financial firms decipher risk of paying for advanced access to market-moving feed",
      "tags": []
    },
    {
      "id": "b79c7e58d03a",
      "title": "Laura Loomer meets Zelenskyy after pro-Ukraine conversion",
      "source": "International homepage",
      "url": "https://www.ft.com/content/ed9baeee-aabc-458a-a161-a607032d158d?syn-25a6b1a6=1",
      "published_at": "2026-07-23T12:30:45+00:00",
      "category": "other",
      "sentiment": "neutral",
      "signal": "watch",
      "summary": "Far-right influencer abandoned opposition to war to praise Kyiv’s resilience against Russian aggression",
      "tags": []
    },
    {
      "id": "78f7a83e386d",
      "title": "Here’s what happened in crypto today",
      "source": "Cointelegraph.com News",
      "url": "https://cointelegraph.com/news/what-happened-in-crypto-today?utm_source=rss_feed&utm_medium=rss&utm_campaign=rss_partner_inbound",
      "published_at": "2026-07-23T13:31:28+00:00",
      "category": "other",
      "sentiment": "neutral",
      "signal": "watch",
      "summary": "<p style=\"float: right; margin: 0 0 10px 15px; width: 240px;\"><img alt=\"Here’s what happened in crypto today\" class=\"type:primaryImage\" src=\"https://s3-images.ctmedia.io/media/article-covers/article-c",
      "tags": []
    },
    {
      "id": "817247f9b091",
      "title": "Fears of AI-driven DeFi hack epidemic overstated for now — but not for long",
      "source": "Cointelegraph.com News",
      "url": "https://cointelegraph.com/magazine/ai-hasnt-unleashed-a-defi-hackpocalypse-but-its-making-every-weakness-more-dangerous?utm_source=rss_feed&utm_medium=rss&utm_campaign=rss_partner_inbound",
      "published_at": "2026-07-23T13:30:00+00:00",
      "category": "other",
      "sentiment": "neutral",
      "signal": "watch",
      "summary": "<p style=\"float: right; margin: 0 0 10px 15px; width: 240px;\"><img alt=\"Fears of AI-driven DeFi hack epidemic overstated for now — but not for long \" class=\"type:primaryImage\" src=\"https://s3-images.c",
      "tags": []
    },
    {
      "id": "e7e525cda515",
      "title": "Binance joins STOP THE TRAFFIK in anti-human trafficking effort",
      "source": "Cointelegraph.com News",
      "url": "https://cointelegraph.com/news/binance-stop-the-traffik-anti-human-trafficking?utm_source=rss_feed&utm_medium=rss&utm_campaign=rss_partner_inbound",
      "published_at": "2026-07-23T13:22:00+00:00",
      "category": "other",
      "sentiment": "neutral",
      "signal": "watch",
      "summary": "<p style=\"float: right; margin: 0 0 10px 15px; width: 240px;\"><img alt=\"Binance joins STOP THE TRAFFIK in anti-human trafficking effort\" class=\"type:primaryImage\" src=\"https://s3-images.ctmedia.io/med",
      "tags": []
    },
    {
      "id": "422282f9d47e",
      "title": "Strategy-led group pledges $15M to quantum-proof Bitcoin network",
      "source": "Cointelegraph.com News",
      "url": "https://cointelegraph.com/news/strategy-consortium-15m-quantum-proof-bitcoin?utm_source=rss_feed&utm_medium=rss&utm_campaign=rss_partner_inbound",
      "published_at": "2026-07-23T13:03:18+00:00",
      "category": "other",
      "sentiment": "neutral",
      "signal": "watch",
      "summary": "<p style=\"float: right; margin: 0 0 10px 15px; width: 240px;\"><img alt=\"Strategy-led group pledges $15M to quantum-proof Bitcoin network\" class=\"type:primaryImage\" src=\"https://s3-images.ctmedia.io/me",
      "tags": []
    },
    {
      "id": "9226da91a287",
      "title": "Bitget secures license for New Zealand expansion",
      "source": "Cointelegraph.com News",
      "url": "https://cointelegraph.com/news/bitget-secures-license-new-zealand-expansion?utm_source=rss_feed&utm_medium=rss&utm_campaign=rss_partner_inbound",
      "published_at": "2026-07-23T12:33:07+00:00",
      "category": "other",
      "sentiment": "neutral",
      "signal": "watch",
      "summary": "<p style=\"float: right; margin: 0 0 10px 15px; width: 240px;\"><img alt=\"Bitget secures license for New Zealand expansion\" class=\"type:primaryImage\" src=\"https://s3-images.ctmedia.io/media/article-cove",
      "tags": []
    },
    {
      "id": "ad6c63a4219c",
      "title": "BitMEX token crashes 90% as exchange announces shutdown",
      "source": "Cointelegraph.com News",
      "url": "https://cointelegraph.com/markets/bitmex-token-crashes-90-as-exchange-announces-shutdown?utm_source=rss_feed&utm_medium=rss&utm_campaign=rss_partner_inbound",
      "published_at": "2026-07-23T12:02:00+00:00",
      "category": "other",
      "sentiment": "neutral",
      "signal": "watch",
      "summary": "<p style=\"float: right; margin: 0 0 10px 15px; width: 240px;\"><img alt=\"BitMEX token crashes 90% as exchange announces shutdown\" class=\"type:primaryImage\" src=\"https://s3-images.ctmedia.io/media/artic",
      "tags": []
    },
    {
      "id": "8a68346aa151",
      "title": "Bernstein says Bitcoin mining deals necessary for AI power crunch",
      "source": "Cointelegraph.com News",
      "url": "https://cointelegraph.com/news/bernstein-bitcoin-mining-deals-necessary-ai-power-crunch?utm_source=rss_feed&utm_medium=rss&utm_campaign=rss_partner_inbound",
      "published_at": "2026-07-23T11:49:00+00:00",
      "category": "other",
      "sentiment": "neutral",
      "signal": "watch",
      "summary": "<p style=\"float: right; margin: 0 0 10px 15px; width: 240px;\"><img alt=\"Bernstein says Bitcoin mining deals necessary for AI power crunch\" class=\"type:primaryImage\" src=\"https://s3-images.ctmedia.io/m",
      "tags": []
    },
    {
      "id": "2f2cd8df497e",
      "title": "HYPE falls as crypto funds queue nearly $150M in locked tokens for withdrawal",
      "source": "Cointelegraph.com News",
      "url": "https://cointelegraph.com/markets/hype-falls-as-crypto-funds-queue-nearly-150m-in-locked-tokens-for-withdrawal?utm_source=rss_feed&utm_medium=rss&utm_campaign=rss_partner_inbound",
      "published_at": "2026-07-23T11:24:09+00:00",
      "category": "other",
      "sentiment": "neutral",
      "signal": "watch",
      "summary": "<p style=\"float: right; margin: 0 0 10px 15px; width: 240px;\"><img alt=\"HYPE falls as crypto funds queue nearly $150M in locked tokens for withdrawal\" class=\"type:primaryImage\" src=\"https://s3-images.",
      "tags": []
    },
    {
      "id": "f72402259d78",
      "title": "Kazakhstan approves strategic crypto mining rules tied to national reserve",
      "source": "Cointelegraph.com News",
      "url": "https://cointelegraph.com/news/kazakhstan-strategic-crypto-mining-national-reserve?utm_source=rss_feed&utm_medium=rss&utm_campaign=rss_partner_inbound",
      "published_at": "2026-07-23T11:04:42+00:00",
      "category": "other",
      "sentiment": "neutral",
      "signal": "watch",
      "summary": "<p style=\"float: right; margin: 0 0 10px 15px; width: 240px;\"><img alt=\"Kazakhstan approves strategic crypto mining rules tied to national reserve\" class=\"type:primaryImage\" src=\"https://s3-images.ctm",
      "tags": []
    },
    {
      "id": "88b9066c112e",
      "title": "Bitcoin will get ‘lift’ from Hyperliquid, Robinhood in next crypto bull market: Bitwise exec",
      "source": "Cointelegraph.com News",
      "url": "https://cointelegraph.com/markets/bitcoin-will-get-lift-from-hyperliquid-robinhood-in-next-crypto-bull-market-bitwise-exec?utm_source=rss_feed&utm_medium=rss&utm_campaign=rss_partner_inbound",
      "published_at": "2026-07-23T10:49:00+00:00",
      "category": "other",
      "sentiment": "neutral",
      "signal": "watch",
      "summary": "<p style=\"float: right; margin: 0 0 10px 15px; width: 240px;\"><img alt=\"Bitcoin will get ‘lift’ from Hyperliquid, Robinhood in next crypto bull market: Bitwise exec\" class=\"type:primaryImage\" src=\"htt",
      "tags": []
    },
    {
      "id": "3bfe4064ae89",
      "title": "The SEC settles with Coinbase over its missing Gary Gensler texts",
      "source": "CoinDesk: Bitcoin, Ethereum, Crypto News and Price Data",
      "url": "https://www.coindesk.com/policy/2026/07/23/sec-agrees-to-end-lawsuit-over-missing-ethereum-records-will-pay-usd150-000-in-fees",
      "published_at": "2026-07-23T15:36:39+00:00",
      "category": "other",
      "sentiment": "neutral",
      "signal": "watch",
      "summary": "The SEC settles with Coinbase over its missing Gary Gensler texts",
      "tags": []
    },
    {
      "id": "ddef07f906b1",
      "title": "Crypto for Advisors: It’s time for tokenization to get to work",
      "source": "CoinDesk: Bitcoin, Ethereum, Crypto News and Price Data",
      "url": "https://www.coindesk.com/coindesk-indices/2026/07/23/crypto-for-advisors-it-s-time-for-tokenization-to-get-to-work",
      "published_at": "2026-07-23T14:53:34+00:00",
      "category": "other",
      "sentiment": "neutral",
      "signal": "watch",
      "summary": "Crypto for Advisors: It’s time for tokenization to get to work",
      "tags": []
    },
    {
      "id": "358c4fd6015b",
      "title": "Uniswap pushes deeper into tokenized assets with permissioned trading pools",
      "source": "CoinDesk: Bitcoin, Ethereum, Crypto News and Price Data",
      "url": "https://www.coindesk.com/business/2026/07/22/uniswap-pushes-deeper-into-tokenized-assets-with-permissioned-trading-pools",
      "published_at": "2026-07-23T14:00:00+00:00",
      "category": "other",
      "sentiment": "neutral",
      "signal": "watch",
      "summary": "Uniswap pushes deeper into tokenized assets with permissioned trading pools",
      "tags": []
    },
    {
      "id": "b5a410f53186",
      "title": "Goldman Sachs CEO backs Clarity Act despite banking industry's concerns over stablecoin rules",
      "source": "CoinDesk: Bitcoin, Ethereum, Crypto News and Price Data",
      "url": "https://www.coindesk.com/policy/2026/07/23/goldman-sachs-ceo-backs-clarity-act-despite-banking-industry-s-concerns-over-stablecoin-rules",
      "published_at": "2026-07-23T13:53:19+00:00",
      "category": "other",
      "sentiment": "neutral",
      "signal": "watch",
      "summary": "Goldman Sachs CEO backs Clarity Act despite banking industry's concerns over stablecoin rules",
      "tags": []
    },
    {
      "id": "e51ed2e75282",
      "title": "The KIDS Act is way worse than digital carding — it is a mass surveillance system",
      "source": "CoinDesk: Bitcoin, Ethereum, Crypto News and Price Data",
      "url": "https://www.coindesk.com/opinion/2026/07/23/the-kids-act-is-way-worse-than-digital-carding-it-is-a-mass-surveillance-system",
      "published_at": "2026-07-23T13:00:00+00:00",
      "category": "other",
      "sentiment": "neutral",
      "signal": "watch",
      "summary": "The KIDS Act is way worse than digital carding — it is a mass surveillance system",
      "tags": []
    },
    {
      "id": "94f0fd4bdf4d",
      "title": "BlackRock, Coinbase, Strategy in a new group pledging $15 million to prepare Bitcoin for quantum threats",
      "source": "CoinDesk: Bitcoin, Ethereum, Crypto News and Price Data",
      "url": "https://www.coindesk.com/business/2026/07/23/blackrock-coinbase-strategy-in-group-pledging-usd15-million-to-prepare-bitcoin-for-quantum-threats",
      "published_at": "2026-07-23T12:54:27+00:00",
      "category": "other",
      "sentiment": "neutral",
      "signal": "watch",
      "summary": "BlackRock, Coinbase, Strategy in a new group pledging $15 million to prepare Bitcoin for quantum threats",
      "tags": []
    },
    {
      "id": "7c5b73a77b42",
      "title": "Abu Dhabi's Mubadala Capital joins tokenization push as Coinbase takes stake in onchain fund",
      "source": "CoinDesk: Bitcoin, Ethereum, Crypto News and Price Data",
      "url": "https://www.coindesk.com/business/2026/07/23/abu-dhabi-s-mubadala-capital-joins-tokenization-push-as-coinbase-takes-stake-in-onchain-fund",
      "published_at": "2026-07-23T12:00:00+00:00",
      "category": "other",
      "sentiment": "neutral",
      "signal": "watch",
      "summary": "Abu Dhabi's Mubadala Capital joins tokenization push as Coinbase takes stake in onchain fund",
      "tags": []
    },
    {
      "id": "5b5fcbe22fdc",
      "title": "Polymarket to challenge France’s nationwide website block",
      "source": "CoinDesk: Bitcoin, Ethereum, Crypto News and Price Data",
      "url": "https://www.coindesk.com/policy/2026/07/23/polymarket-to-challenge-france-s-nationwide-website-block",
      "published_at": "2026-07-23T11:53:53+00:00",
      "category": "other",
      "sentiment": "neutral",
      "signal": "watch",
      "summary": "Polymarket to challenge France’s nationwide website block",
      "tags": []
    },
    {
      "id": "838e0781c2dd",
      "title": "Bulls face a test unlike anything in bitcoin's 17-year history",
      "source": "CoinDesk: Bitcoin, Ethereum, Crypto News and Price Data",
      "url": "https://www.coindesk.com/daybook-us/2026/07/23/bulls-face-a-test-unlike-anything-in-bitcoin-s-17-year-history",
      "published_at": "2026-07-23T11:13:39+00:00",
      "category": "other",
      "sentiment": "neutral",
      "signal": "watch",
      "summary": "Bulls face a test unlike anything in bitcoin's 17-year history",
      "tags": []
    },
    {
      "id": "b1bed9b2c5e7",
      "title": "Crypto catches its breath as bitcoin settles into a holding pattern amid July rally",
      "source": "CoinDesk: Bitcoin, Ethereum, Crypto News and Price Data",
      "url": "https://www.coindesk.com/markets/2026/07/23/crypto-catches-its-breath-as-bitcoin-settles-into-a-holding-pattern-after-its-best-month-since-january",
      "published_at": "2026-07-23T10:26:23+00:00",
      "category": "other",
      "sentiment": "neutral",
      "signal": "watch",
      "summary": "Crypto catches its breath as bitcoin settles into a holding pattern amid July rally",
      "tags": []
    },
    {
      "id": "ab6e279b218f",
      "title": "Acadian Asset Management: Systematic Gains",
      "source": "All Articles on Seeking Alpha",
      "url": "https://seekingalpha.com/article/4924821-acadian-asset-management-systematic-gains?source=feed_all_articles",
      "published_at": "2026-07-23T16:32:18+00:00",
      "category": "other",
      "sentiment": "neutral",
      "signal": "watch",
      "summary": "Acadian Asset Management: Systematic Gains",
      "tags": []
    },
    {
      "id": "3609fa910896",
      "title": "Givaudan SA (GVDNY) Q2 2026 Earnings Call Transcript",
      "source": "All Articles on Seeking Alpha",
      "url": "https://seekingalpha.com/article/4924637-givaudan-sa-gvdny-q2-2026-earnings-call-transcript?source=feed_all_articles",
      "published_at": "2026-07-23T16:31:02+00:00",
      "category": "other",
      "sentiment": "neutral",
      "signal": "watch",
      "summary": "Givaudan SA (GVDNY) Q2 2026 Earnings Call Transcript",
      "tags": []
    },
    {
      "id": "01d90f04ce7e",
      "title": "REIT Rebound: 3 Top REITs Averaging 9.8% FWD Yield",
      "source": "All Articles on Seeking Alpha",
      "url": "https://seekingalpha.com/article/4924851-reit-rebound-3-top-reits-averaging-9-8-percent-fwd-yield?source=feed_all_articles",
      "published_at": "2026-07-23T16:31:00+00:00",
      "category": "other",
      "sentiment": "neutral",
      "signal": "watch",
      "summary": "REIT Rebound: 3 Top REITs Averaging 9.8% FWD Yield",
      "tags": []
    },
    {
      "id": "08dbc11f39b4",
      "title": "T-Mobile US, Inc. (TMUS) Q2 2026 Earnings Call Transcript",
      "source": "All Articles on Seeking Alpha",
      "url": "https://seekingalpha.com/article/4924740-t-mobile-us-inc-tmus-q2-2026-earnings-call-transcript?source=feed_all_articles",
      "published_at": "2026-07-23T16:30:58+00:00",
      "category": "other",
      "sentiment": "neutral",
      "signal": "watch",
      "summary": "T-Mobile US, Inc. (TMUS) Q2 2026 Earnings Call Transcript",
      "tags": []
    },
    {
      "id": "8e569e9aa228",
      "title": "Nestlé S.A. (NEST:CA) Q2 2026 Earnings Call Transcript",
      "source": "All Articles on Seeking Alpha",
      "url": "https://seekingalpha.com/article/4924586-nestle-s-a-nest-ca-q2-2026-earnings-call-transcript?source=feed_all_articles",
      "published_at": "2026-07-23T16:30:57+00:00",
      "category": "other",
      "sentiment": "neutral",
      "signal": "watch",
      "summary": "Nestlé S.A. (NEST:CA) Q2 2026 Earnings Call Transcript",
      "tags": []
    },
    {
      "id": "28e4807a2017",
      "title": "Horizon Bancorp, Inc. (HBNC) Q2 2026 Earnings Call Transcript",
      "source": "All Articles on Seeking Alpha",
      "url": "https://seekingalpha.com/article/4924850-horizon-bancorp-inc-hbnc-q2-2026-earnings-call-transcript?source=feed_all_articles",
      "published_at": "2026-07-23T16:30:52+00:00",
      "category": "other",
      "sentiment": "neutral",
      "signal": "watch",
      "summary": "Horizon Bancorp, Inc. (HBNC) Q2 2026 Earnings Call Transcript",
      "tags": []
    },
    {
      "id": "07c5ce63ea4e",
      "title": "ALPEK, S.A.B. de C.V. 2026 Q2 - Results - Earnings Call Presentation",
      "source": "All Articles on Seeking Alpha",
      "url": "https://seekingalpha.com/article/4924863-alpek-s-a-b-de-c-v-2026-q2-results-earnings-call-presentation?source=feed_all_articles",
      "published_at": "2026-07-23T16:30:50+00:00",
      "category": "other",
      "sentiment": "neutral",
      "signal": "watch",
      "summary": "ALPEK, S.A.B. de C.V. 2026 Q2 - Results - Earnings Call Presentation",
      "tags": []
    },
    {
      "id": "ce1dc236d92b",
      "title": "ServiceNow: Debunking The 2 Biggest Bear Arguments",
      "source": "All Articles on Seeking Alpha",
      "url": "https://seekingalpha.com/article/4924812-servicenow-debunking-the-two-biggest-bear-arguments?source=feed_all_articles",
      "published_at": "2026-07-23T16:28:00+00:00",
      "category": "other",
      "sentiment": "neutral",
      "signal": "watch",
      "summary": "ServiceNow: Debunking The 2 Biggest Bear Arguments",
      "tags": []
    },
    {
      "id": "c09b9bccbbc2",
      "title": "Confluence Investment Management's Keller Q1 2026 Quarterly",
      "source": "All Articles on Seeking Alpha",
      "url": "https://seekingalpha.com/article/4924813-confluence-investment-managements-keller-q1-2026-quarterly?source=feed_all_articles",
      "published_at": "2026-07-23T16:28:00+00:00",
      "category": "other",
      "sentiment": "neutral",
      "signal": "watch",
      "summary": "Confluence Investment Management's Keller Q1 2026 Quarterly",
      "tags": []
    },
    {
      "id": "a22043b87304",
      "title": "Climb Bio: Three Key Kidney Disease Readouts In Q4 Ought To Generate Volatility",
      "source": "All Articles on Seeking Alpha",
      "url": "https://seekingalpha.com/article/4924811-climb-bio-three-key-kidney-disease-readouts-q4-ought-to-generate-volatility?source=feed_all_articles",
      "published_at": "2026-07-23T16:27:00+00:00",
      "category": "other",
      "sentiment": "neutral",
      "signal": "watch",
      "summary": "Climb Bio: Three Key Kidney Disease Readouts In Q4 Ought To Generate Volatility",
      "tags": []
    }
  ]
}